nameko_wrapper/__init__.py
nameko_wrapper/config.py
nameko_wrapper/custom_enum.py
nameko_wrapper/dependency_providers.py
nameko_wrapper/exceptions.py
nameko_wrapper/logger.py
nameko_wrapper/pagination.py
nameko_wrapper/response.py
nameko_wrapper/rpc.py
nameko_wrapper/share.py
nameko_wrapper/dependency_providers/__init__.py
nameko_wrapper/dependency_providers/crontab.py
nameko_wrapper/dependency_providers/logger.py
nameko_wrapper/dependency_providers/redis.py
nameko_wrapper/elasticsearch/__init__.py
nameko_wrapper/elasticsearch/dependency_providers.py
nameko_wrapper/elasticsearch/documents.py
nameko_wrapper/elasticsearch/exceptions.py
nameko_wrapper/elasticsearch/searches.py
nameko_wrapper/elasticsearch/utils/__init__.py
nameko_wrapper/elasticsearch/utils/formatters.py
nameko_wrapper/log/__init__.py
nameko_wrapper/log/logger.py
nameko_wrapper/marshmallow/__init__.py
nameko_wrapper/marshmallow/validate.py
nameko_wrapper/redis/__init__.py
nameko_wrapper/redis/dependency_providers.py
nameko_wrapper/service/__init__.py
nameko_wrapper/service/payload.py
nameko_wrapper/utils/__init__.py
nameko_wrapper/utils/converts.py
nameko_wrapper-0.0.30.dist-info/LICENSE
nameko_wrapper-0.0.30.dist-info/METADATA
nameko_wrapper-0.0.30.dist-info/WHEEL
nameko_wrapper-0.0.30.dist-info/top_level.txt
nameko_wrapper-0.0.30.dist-info/RECORD
