Metadata-Version: 2.1
Name: nameko-wrapper
Version: 0.0.30
Summary: nameko wrapper
Home-page: https://github.com/li1234yun/nameko-wrapper
Author: li1234yun
Author-email: li1234yun@163.com
License: UNKNOWN
Platform: UNKNOWN
Classifier: Programming Language :: Python :: 3
Classifier: License :: OSI Approved :: MIT License
Classifier: Operating System :: OS Independent
Requires-Dist: nameko
Requires-Dist: marshmallow (>2)
